{
  "project_info": {
    "project_number": "949010873539",
    "project_id": "rising-distributor",
    "storage_bucket": "rising-distributor.firebasestorage.app"
  },
  "client": [
    {
      "client_info": {
        "mobilesdk_app_id": "1:949010873539:android:47fd0c1c7d6c938b2a7676",
        "android_client_info": {
          "package_name": "com.rising.raising_india"
        }
      },
      "oauth_client": [],
      "api_key": [
        {
          "current_key": "AIzaSyBgQAZoFUhrJGjuvcfL_PLphZSQxzczCJI"
        }
      ],
      "services": {
        "appinvite_service": {
          "other_platform_oauth_client": []
        }
      }
    }
  ],
  "configuration_version": "1"
}